nxscli_np/__init__.py
nxscli_np/ext_commands.py
nxscli_np/ext_plugins.py
nxscli_np/commands/cmd_npmem.py
nxscli_np/commands/cmd_npsave.py
nxscli_np/plugins/npmem.py
nxscli_np/plugins/npsave.py
nxscli_np-0.5.0.dist-info/LICENSE
nxscli_np-0.5.0.dist-info/METADATA
nxscli_np-0.5.0.dist-info/WHEEL
nxscli_np-0.5.0.dist-info/entry_points.txt
nxscli_np-0.5.0.dist-info/top_level.txt
nxscli_np-0.5.0.dist-info/RECORD
