Metadata-Version: 2.1
Name: nxscli-np
Version: 0.5.0
Summary: Nxscli Numpy extension
Author-email: raiden00 <raiden00@railab.me>
License: Apache-2.0
Project-URL: Changelog, https://github.com/railab/nxscli-np/blob/master/CHANGES.md
Project-URL: Homepage, https://github.com/railab/nxscli-np
Keywords: nuttx,nxscli
Classifier: Development Status :: 4 - Beta
Classifier: Intended Audience :: Developers
Classifier: License :: OSI Approved :: Apache Software License
Classifier: Programming Language :: Python :: 3.10
Classifier: Programming Language :: Python :: 3.11
Classifier: Topic :: Software Development :: Embedded Systems
Classifier: Operating System :: OS Independent
Requires-Python: >=3.10
License-File: LICENSE
Requires-Dist: nxscli (>=0.5.0)
Requires-Dist: numpy (>=1.24.2)
Requires-Dist: click (>=8.1)
